rsplib
