Metadata-Version: 1.0
Name: rsplib
Version: 0.3.3.5
Summary: RSP python library
Home-page: https://github.com/riccardotommasini/rsplib
Author: Riccardo Tommasini
Author-email: riccardo.tommasini@polimi.it
License: MIT
Platform: UNKNOWN
